importreqs/__init__.py
importreqs/cli.py
importreqs/importreqs.py
importreqs-0.3.1.dist-info/LICENSE
importreqs-0.3.1.dist-info/METADATA
importreqs-0.3.1.dist-info/WHEEL
importreqs-0.3.1.dist-info/entry_points.txt
importreqs-0.3.1.dist-info/top_level.txt
importreqs-0.3.1.dist-info/RECORD
