Metadata-Version: 2.1
Name: importreqs
Version: 0.3.1
Summary: UNKNOWN
Home-page: https://github.com/gstianfu/importreqs
Author: the AUTHORS of importreqs
Author-email: UNKNOWN
License: UNKNOWN
Platform: UNKNOWN
Classifier: Environment :: Console
Classifier: Intended Audience :: Developers
Classifier: License :: OSI Approved :: Apache Software License
Classifier: Programming Language :: Python
Requires-Dist: pip
